MANIFEST.in
README.rst
setup.py
darcsver/__init__.py
darcsver/_version.py
darcsver/darcsvermodule.py
darcsver/setuptools_command.py
darcsver.egg-info/PKG-INFO
darcsver.egg-info/SOURCES.txt
darcsver.egg-info/dependency_links.txt
darcsver.egg-info/entry_points.txt
darcsver.egg-info/not-zip-safe
darcsver.egg-info/top_level.txt
darcsver/test/__init__.py
darcsver/test/test_darcsver.py
scripts/__init__.py
scripts/darcsverscript.py