Metadata-Version: 1.0
Name: darcsver
Version: 1.7.4
Summary: generate a version number from darcs history
Home-page: https://tahoe-lafs.org/trac/darcsver
Author: Zooko O'Whielacronx
Author-email: zooko@zooko.com
License: BSD
Keywords: distutils setuptools plugin setup darcs
Platform: UNKNOWN
Classifier: Framework :: Setuptools Plugin
Classifier: Development Status :: 5 - Production/Stable
Classifier: License :: OSI Approved :: BSD License
Classifier: License :: DFSG approved
Classifier: Intended Audience :: Developers
Classifier: Operating System :: OS Independent
Classifier: Natural Language :: English
Classifier: Programming Language :: Python
Classifier: Programming Language :: Python :: 2
Classifier: Programming Language :: Python :: 2.4
Classifier: Programming Language :: Python :: 2.5
Classifier: Programming Language :: Python :: 2.6
Classifier: Programming Language :: Python :: 2.7
Classifier: Topic :: Utilities
Classifier: Topic :: Software Development :: Libraries
